sigma_ai/__init__.py
sigma_ai/cli.py
sigma_ai-0.1.0.dist-info/METADATA
sigma_ai-0.1.0.dist-info/WHEEL
sigma_ai-0.1.0.dist-info/entry_points.txt
sigma_ai-0.1.0.dist-info/top_level.txt
sigma_ai-0.1.0.dist-info/RECORD
