Metadata-Version: 2.4
Name: sigma-ai
Version: 0.1.0
Summary: Comparative evaluation harness to benchmark local vs cloud LLMs
Author: Andrii Meleshkov
License: MIT
Project-URL: Homepage, https://github.com/andrwl1/sigma-ai
Requires-Python: >=3.9
Provides-Extra: dev
Requires-Dist: pytest; extra == "dev"
